hit_acs/DVM-Parameter_v2.10.0-HIT.csv
hit_acs/__init__.py
hit_acs/beamoptikdll.py
hit_acs/beamoptikstub.py
hit_acs/dvm_parameters.py
hit_acs/gui_qt.py
hit_acs/gui_win32.py
hit_acs/gui_wx.py
hit_acs/offsets.py
hit_acs/plugin.py
hit_acs/util.py
hit_acs-20.1.0.dist-info/METADATA
hit_acs-20.1.0.dist-info/WHEEL
hit_acs-20.1.0.dist-info/entry_points.txt
hit_acs-20.1.0.dist-info/top_level.txt
hit_acs-20.1.0.dist-info/zip-safe
hit_acs-20.1.0.dist-info/RECORD
