Metadata-Version: 2.1
Name: hit-acs
Version: 20.1.0
Summary: Tools for the accelerator control system of the HIT facility.
Home-page: https://github.com/hibtc/hit_acs
Author: Thomas Gläßle
Author-email: t_glaessle@gmx.de
Maintainer: Cristopher Cortés
Maintainer-email: ecortesg95@gmail.com
License: UNKNOWN
Platform: UNKNOWN
Classifier: Development Status :: 3 - Alpha
Classifier: Intended Audience :: Developers
Classifier: Intended Audience :: Healthcare Industry
Classifier: Intended Audience :: Science/Research
Classifier: Operating System :: OS Independent
Classifier: Programming Language :: Python
Classifier: Topic :: Scientific/Engineering :: Medical Science Apps.
Classifier: Topic :: Scientific/Engineering :: Physics
Requires-Python: >=2.7
Requires-Dist: pydicti (>=0.0.4)
Requires-Dist: importlib-resources
